[
  {
    "h": "Norway",
    "a": "France",
    "home": 0.192,
    "draw": 0.209,
    "away": 0.599,
    "_src": "DraftKings via ESPN, close, 06/26"
  },
  {
    "h": "Senegal",
    "a": "Iraq",
    "home": 0.773,
    "draw": 0.147,
    "away": 0.08,
    "_src": "DraftKings via ESPN, close, 06/26"
  },
  {
    "h": "Cape Verde",
    "a": "Saudi Arabia",
    "home": 0.361,
    "draw": 0.285,
    "away": 0.354,
    "_src": "DraftKings via ESPN, close, 06/26"
  },
  {
    "h": "Uruguay",
    "a": "Spain",
    "home": 0.12,
    "draw": 0.24,
    "away": 0.64,
    "_src": "DraftKings via ESPN, close, 06/26"
  },
  {
    "h": "Egypt",
    "a": "Iran",
    "home": 0.381,
    "draw": 0.374,
    "away": 0.245,
    "_src": "DraftKings via ESPN, close, 06/26"
  },
  {
    "h": "New Zealand",
    "a": "Belgium",
    "home": 0.06,
    "draw": 0.113,
    "away": 0.826,
    "_src": "DraftKings via ESPN, close, 06/26"
  },
  {
    "h": "Croatia",
    "a": "Ghana",
    "home": 0.543,
    "draw": 0.282,
    "away": 0.175,
    "_src": "DraftKings via ESPN, close, 06/27"
  },
  {
    "h": "Panama",
    "a": "England",
    "home": 0.064,
    "draw": 0.12,
    "away": 0.816,
    "_src": "DraftKings via ESPN, close, 06/27"
  },
  {
    "h": "Colombia",
    "a": "Portugal",
    "home": 0.227,
    "draw": 0.251,
    "away": 0.521,
    "_src": "DraftKings via ESPN, close, 06/27"
  },
  {
    "h": "DR Congo",
    "a": "Uzbekistan",
    "home": 0.552,
    "draw": 0.229,
    "away": 0.219,
    "_src": "DraftKings via ESPN, close, 06/27"
  },
  {
    "h": "Algeria",
    "a": "Austria",
    "home": 0.234,
    "draw": 0.436,
    "away": 0.331,
    "_src": "DraftKings via ESPN, close, 06/27"
  },
  {
    "h": "Argentina",
    "a": "Jordan",
    "home": 0.809,
    "draw": 0.127,
    "away": 0.064,
    "_src": "DraftKings via ESPN, close, 06/27"
  }
]
